MANIFEST.in
README.txt
header.txt
setup.cfg
setup.py
zopeskel.txt
zopyx.multieventcalendar-configure.zcml
docs/HISTORY.txt
docs/INSTALL.txt
docs/LICENCE.txt
docs/LICENSE.GPL
docs/LICENSE.txt
zopyx/__init__.py
zopyx.multieventcalendar.egg-info/PKG-INFO
zopyx.multieventcalendar.egg-info/SOURCES.txt
zopyx.multieventcalendar.egg-info/dependency_links.txt
zopyx.multieventcalendar.egg-info/entry_points.txt
zopyx.multieventcalendar.egg-info/namespace_packages.txt
zopyx.multieventcalendar.egg-info/not-zip-safe
zopyx.multieventcalendar.egg-info/requires.txt
zopyx.multieventcalendar.egg-info/top_level.txt
zopyx/multieventcalendar/__init__.py
zopyx/multieventcalendar/configure.zcml
zopyx/multieventcalendar/event_extender.py
zopyx/multieventcalendar/profiles.zcml
zopyx/multieventcalendar/setuphandlers.py
zopyx/multieventcalendar/skins.zcml
zopyx/multieventcalendar/tests.py
zopyx/multieventcalendar/version.txt
zopyx/multieventcalendar/browser/__init__.py
zopyx/multieventcalendar/browser/configure.zcml
zopyx/multieventcalendar/browser/interfaces.py
zopyx/multieventcalendar/browser/viewlet.pt
zopyx/multieventcalendar/browser/viewlets.py
zopyx/multieventcalendar/browser/images/README.txt
zopyx/multieventcalendar/browser/stylesheets/README.txt
zopyx/multieventcalendar/browser/stylesheets/main.css
zopyx/multieventcalendar/profiles/default/import_steps.xml
zopyx/multieventcalendar/profiles/default/metadata.xml
zopyx/multieventcalendar/profiles/default/skins.xml
zopyx/multieventcalendar/profiles/default/viewlets.xml
zopyx/multieventcalendar/profiles/default/zopyx.multieventcalendar_various.txt
zopyx/multieventcalendar/skins/zopyx_multieventcalendar/event_view.pt
zopyx/multieventcalendar/skins/zopyx_multieventcalendar/event_view.pt.metadata
zopyx/multieventcalendar/skins/zopyx_multieventcalendar/zme_calcEvents.py
zopyx/multieventcalendar/skins/zopyx_multieventcalendar/zme_calendar.pt
zopyx/multieventcalendar/skins/zopyx_multieventcalendar/zme_calendarExportVCalendar.py
zopyx/multieventcalendar/skins/zopyx_multieventcalendar/zme_calendarExportVCalendar.py.metadata
zopyx/multieventcalendar/skins/zopyx_multieventcalendar/zme_datesForWeek.py
zopyx/multieventcalendar/skins/zopyx_multieventcalendar/zme_eventsForHour.py
zopyx/multieventcalendar/skins/zopyx_multieventcalendar/zme_eventsForWeek.py
zopyx/multieventcalendar/skins/zopyx_multieventcalendar/zme_eventsWholeDay.py
