Metadata-Version: 1.0
Name: zopyx.multieventcalendar
Version: 0.1.3
Summary: A multi-event calendar for Plone 3.X
Home-page: http://svn.plone.org/svn/collective/zopyx.multieventcalendar
Author: Andreas Jung
Author-email: info@zopyx.com
License: ZPL
Keywords: Event Calendaring Plone
Platform: UNKNOWN
Classifier: Framework :: Plone
Classifier: Programming Language :: Python
Classifier: Topic :: Software Development :: Libraries :: Python Modules
